README
importhelpers.py
setup.py
importhelpers.egg-info/PKG-INFO
importhelpers.egg-info/SOURCES.txt
importhelpers.egg-info/dependency_links.txt
importhelpers.egg-info/top_level.txt