Metadata-Version: 1.0
Name: importhelpers
Version: 0.2
Summary: Common import convenience functions.
Home-page: http://github.com/edwardgeorge/importhelpers/
Author: Edward George
Author-email: edwardgeorge@gmail.com
License: UNKNOWN
Platform: UNKNOWN
Classifier: License :: OSI Approved :: MIT License
Classifier: Programming Language :: Python
Classifier: Intended Audience :: Developers
Classifier: Development Status :: 3 - Alpha
Classifier: Topic :: Software Development :: Libraries :: Python Modules
